qurveros/__init__.py
qurveros/barqtools.py
qurveros/beziertools.py
qurveros/controltools.py
qurveros/frametools.py
qurveros/losses.py
qurveros/misctools.py
qurveros/optspacecurve.py
qurveros/plot_configs.py
qurveros/plottools.py
qurveros/settings.py
qurveros/spacecurve.py
qurveros/qubit_bench/__init__.py
qurveros/qubit_bench/noise_experiments.py
qurveros/qubit_bench/noisetools.py
qurveros/qubit_bench/quantumtools.py
qurveros/qubit_bench/simulator.py
qurveros-1.0.0.dist-info/METADATA
qurveros-1.0.0.dist-info/WHEEL
qurveros-1.0.0.dist-info/licenses/LICENSE.txt
qurveros-1.0.0.dist-info/RECORD
