Metadata-Version: 2.4
Name: qurveros
Version: 1.0.0
Summary: SCQC and BARQ implementation based on JAX.
Project-URL: homepage, https://github.com/evpiliouras/qurveros
Project-URL: repository, https://github.com/evpiliouras/qurveros
Project-URL: issues, https://github.com/evpiliouras/qurveros/ISSUES.md
Author-email: Evangelos Piliouras <piliouras@vt.edu>
License-Expression: BSD-3-Clause-Clear
License-File: LICENSE.txt
Keywords: barq,noise,quantum control,quantum information,robust quantum control,scqc,space curve
Classifier: Intended Audience :: Science/Research
Classifier: Topic :: Scientific/Engineering :: Physics
Requires-Python: >=3.10
Requires-Dist: jax
Requires-Dist: matplotlib
Requires-Dist: numpy
Requires-Dist: optax
Requires-Dist: pandas
Requires-Dist: qutip>=5
Requires-Dist: scipy
Provides-Extra: examples
Requires-Dist: jupyter; extra == 'examples'
Provides-Extra: results
Requires-Dist: filter-functions; extra == 'results'
Requires-Dist: jupyter; extra == 'results'
